uiadmin_fastapi/CoreController.py
uiadmin_fastapi/Uiadmin.py
uiadmin_fastapi/__init__.py
uiadmin_fastapi/utils.py
uiadmin_fastapi/util/__init__.py
uiadmin_fastapi/util/xybuilder/XyBuilderForm.py
uiadmin_fastapi/util/xybuilder/XyBuilderList.py
uiadmin_fastapi/util/xybuilder/__init__.py
Uiadmin_FastApi-1.0.3.dist-info/LICENSE.md
Uiadmin_FastApi-1.0.3.dist-info/METADATA
Uiadmin_FastApi-1.0.3.dist-info/WHEEL
Uiadmin_FastApi-1.0.3.dist-info/top_level.txt
Uiadmin_FastApi-1.0.3.dist-info/RECORD
