Metadata-Version: 2.1
Name: Uiadmin-FastApi
Version: 1.0.3
Summary: uiadmin的python-fastapi实现
Home-page: http://uiadmin.net
Author: jry
Author-email: ijry@qq.com
License: Apache2
Platform: any
Classifier: Environment :: Web Environment
Classifier: Intended Audience :: Developers
Classifier: License :: OSI Approved :: Apache Software License
Classifier: Operating System :: OS Independent
Classifier: Programming Language :: Python
Classifier: Topic :: Internet :: WWW/HTTP :: Dynamic Content
Classifier: Topic :: Software Development :: Libraries :: Python Modules
License-File: LICENSE.md
Requires-Dist: fastapi
